example/callback_server.py
llm_pdf_chunker-0.1.2.dist-info/licenses/LICENSE
pdf_chunker/__init__.py
pdf_chunker/__main__.py
pdf_chunker/cli.py
pdf_chunker/core.py
pdf_chunker/fonts.py
pdf_chunker/images.py
pdf_image_dumper/__init__.py
pdf_image_dumper/cli.py
pdf_image_dumper/runner.py
tests/test_integration_chunking.py
tests/test_smoke.py
llm_pdf_chunker-0.1.2.dist-info/METADATA
llm_pdf_chunker-0.1.2.dist-info/WHEEL
llm_pdf_chunker-0.1.2.dist-info/entry_points.txt
llm_pdf_chunker-0.1.2.dist-info/top_level.txt
llm_pdf_chunker-0.1.2.dist-info/RECORD
