Metadata-Version: 2.4
Name: llm-pdf-chunker
Version: 0.1.2
Summary: LLM-friendly PDF splitter & image optimizer. Chunk PDFs by size and downsample images for RAG/Bedrock.
Author: T.Fujiba
License: MIT License
Project-URL: Repository, https://github.com/fujiba/pdf-chunker
Classifier: Programming Language :: Python :: 3
Classifier: License :: OSI Approved :: MIT License
Classifier: Operating System :: OS Independent
Requires-Python: >=3.11
License-File: LICENSE
Requires-Dist: pikepdf>=6.0.0
Requires-Dist: Pillow>=9.0.0
Provides-Extra: test
Requires-Dist: pytest>=7.0; extra == "test"
Requires-Dist: pytest-cov; extra == "test"
Provides-Extra: dev
Requires-Dist: twine; extra == "dev"
Dynamic: license-file
